simple_frequency_counter/__init__.py
simple_frequency_counter/counter.py
simple_frequency_counter-0.0.2.dist-info/LICENCE
simple_frequency_counter-0.0.2.dist-info/METADATA
simple_frequency_counter-0.0.2.dist-info/WHEEL
simple_frequency_counter-0.0.2.dist-info/top_level.txt
simple_frequency_counter-0.0.2.dist-info/RECORD
