Metadata-Version: 2.1
Name: simple-frequency-counter
Version: 0.0.2
Summary: Calculate word occurences in txt files inside a given folder.
Home-page: https://github.com/PanosGriziotis/Simple-Word-Frequency-Counter
Author: Panos Griziotis
Author-email: griziotisp@gmail.com
Classifier: Programming Language :: Python :: 3
Classifier: License :: OSI Approved :: MIT License
Classifier: Operating System :: OS Independent
Requires-Python: >=3.7
License-File: LICENCE
